cookbase/__init__.py
cookbase/logging.py
cookbase/utils.py
cookbase/db/__init__.py
cookbase/db/exceptions.py
cookbase/db/handler.py
cookbase/db/utils.py
cookbase/graph/__init__.py
cookbase/graph/cbrgraph.py
cookbase/gui/__init__.py
cookbase/gui/utils.py
cookbase/parsers/__init__.py
cookbase/parsers/jsonfoodex.py
cookbase/parsers/termcode.py
cookbase/parsers/utils.py
cookbase/schema/__init__.py
cookbase/schema/builder.py
cookbase/tests/__init__.py
cookbase/tests/test_db.py
cookbase/tests/test_termcode.py
cookbase/tests/test_validation.py
cookbase/validation/__init__.py
cookbase/validation/cba.py
cookbase/validation/cbr.py
cookbase/validation/exceptions.py
cookbase/validation/globals.py
cookbase/validation/rules.py
cookbase-0.1.0.dist-info/LICENSE
cookbase-0.1.0.dist-info/METADATA
cookbase-0.1.0.dist-info/WHEEL
cookbase-0.1.0.dist-info/top_level.txt
cookbase-0.1.0.dist-info/RECORD
