Metadata-Version: 2.1
Name: cookbase
Version: 0.1.0
Summary: A platform to validate, store and manage cooking recipes based on the JSON Cookbase Format.
Home-page: https://github.com/hblanko/cookbase
Author: Hernán Blanco Landa
Author-email: hblanco@pm.me
License: UNKNOWN
Platform: UNKNOWN
Classifier: Programming Language :: Python :: 3
Classifier: License :: OSI Approved :: GNU General Public License v3 (GPLv3)
Classifier: Operating System :: OS Independent
Requires-Python: >=3.7
Requires-Dist: attrs (==19.3.0)
Requires-Dist: jsonschema (==3.2.0)
Requires-Dist: networkx (==2.4)
Requires-Dist: paramiko (==2.7.1)
Requires-Dist: pymongo (==3.10.1)
Requires-Dist: requests (==2.21.0)
Requires-Dist: ruamel.yaml (==0.16.10)
Requires-Dist: uritools (==3.0.0)
